dagshub_annotation_converter/__init__.py
dagshub_annotation_converter/features.py
dagshub_annotation_converter/py.typed
dagshub_annotation_converter/converters/__init__.py
dagshub_annotation_converter/converters/common.py
dagshub_annotation_converter/converters/cvat.py
dagshub_annotation_converter/converters/yolo.py
dagshub_annotation_converter/formats/__init__.py
dagshub_annotation_converter/formats/common.py
dagshub_annotation_converter/formats/cvat/__init__.py
dagshub_annotation_converter/formats/cvat/box.py
dagshub_annotation_converter/formats/cvat/context.py
dagshub_annotation_converter/formats/cvat/ellipse.py
dagshub_annotation_converter/formats/cvat/points.py
dagshub_annotation_converter/formats/cvat/polygon.py
dagshub_annotation_converter/formats/cvat/skeleton.py
dagshub_annotation_converter/formats/label_studio/__init__.py
dagshub_annotation_converter/formats/label_studio/base.py
dagshub_annotation_converter/formats/label_studio/ellipselabels.py
dagshub_annotation_converter/formats/label_studio/keypointlabels.py
dagshub_annotation_converter/formats/label_studio/polygonlabels.py
dagshub_annotation_converter/formats/label_studio/rectanglelabels.py
dagshub_annotation_converter/formats/label_studio/task.py
dagshub_annotation_converter/formats/yolo/__init__.py
dagshub_annotation_converter/formats/yolo/bbox.py
dagshub_annotation_converter/formats/yolo/categories.py
dagshub_annotation_converter/formats/yolo/common.py
dagshub_annotation_converter/formats/yolo/context.py
dagshub_annotation_converter/formats/yolo/pose.py
dagshub_annotation_converter/formats/yolo/result_import.py
dagshub_annotation_converter/formats/yolo/segmentation.py
dagshub_annotation_converter/ir/__init__.py
dagshub_annotation_converter/ir/image/__init__.py
dagshub_annotation_converter/ir/image/common.py
dagshub_annotation_converter/ir/image/annotations/__init__.py
dagshub_annotation_converter/ir/image/annotations/base.py
dagshub_annotation_converter/ir/image/annotations/bbox.py
dagshub_annotation_converter-0.1.14.dist-info/METADATA
dagshub_annotation_converter-0.1.14.dist-info/WHEEL
dagshub_annotation_converter-0.1.14.dist-info/RECORD
