Metadata-Version: 2.4
Name: dagshub-annotation-converter
Version: 0.1.14
Summary: Annotation converter between different formats
Project-URL: Documentation, https://github.com/dagshub/dagshub-annotation-converter#readme
Project-URL: Issues, https://github.com/dagshub/dagshub-annotation-converter/issues
Project-URL: Source, https://github.com/dagshub/dagshub-annotation-converter
Author-email: Kirill Bolashev <kirill@dagshub.com>
License-Expression: MIT
Classifier: Development Status :: 4 - Beta
Classifier: License :: OSI Approved :: MIT License
Classifier: Programming Language :: Python
Classifier: Programming Language :: Python :: 3.8
Classifier: Programming Language :: Python :: 3.9
Classifier: Programming Language :: Python :: 3.10
Classifier: Programming Language :: Python :: 3.11
Classifier: Programming Language :: Python :: 3.12
Classifier: Programming Language :: Python :: Implementation :: CPython
Classifier: Programming Language :: Python :: Implementation :: PyPy
Requires-Python: >=3.8
Requires-Dist: lxml
Requires-Dist: pandas
Requires-Dist: pillow
Requires-Dist: pydantic>=2.0.0
Requires-Dist: pyyaml
Requires-Dist: typing-extensions
